taktile_auth/__init__.py
taktile_auth/assets/resources.yaml
taktile_auth/assets/roles.yaml
taktile_auth/client.py
taktile_auth/entities/__init__.py
taktile_auth/entities/permission.py
taktile_auth/entities/resource.py
taktile_auth/entities/role.py
taktile_auth/enums.py
taktile_auth/exceptions.py
taktile_auth/parser/__init__.py
taktile_auth/parser/utils.py
taktile_auth/parser/yaml_parsing.py
taktile_auth/py.typed
taktile_auth/schemas/__init__.py
taktile_auth/schemas/session.py
taktile_auth/schemas/token.py
taktile_auth/settings.py
taktile_auth/test_utils/__init__.py
taktile_auth/test_utils/cache_test_utils.py
taktile_auth/test_utils/jwt_test_utils.py
taktile_auth/utils/__init__.py
taktile_auth/utils/cache.py
taktile_auth/utils/sqlalchemy.py
taktile_auth-1.1.72.dist-info/METADATA
taktile_auth-1.1.72.dist-info/WHEEL
taktile_auth-1.1.72.dist-info/RECORD
