Metadata-Version: 2.3
Name: taktile-auth
Version: 1.1.72
Summary: Auth Package for Taktile
License: Apache-2.0
Author: Taktile GmbH
Author-email: devops@taktile.com
Requires-Python: >=3.10,<4.0
Classifier: License :: OSI Approved :: Apache Software License
Classifier: Programming Language :: Python :: 3
Classifier: Programming Language :: Python :: 3.10
Classifier: Programming Language :: Python :: 3.11
Classifier: Programming Language :: Python :: 3.12
Classifier: Programming Language :: Python :: 3.13
Requires-Dist: PyJWT[crypto] (==2.10.1)
Requires-Dist: PyYAML (>=6.0,<7.0)
Requires-Dist: cryptography (>=44.0.1,<45.0.0)
Requires-Dist: pydantic (<3.0)
Requires-Dist: requests (>=2.32,<3.0)
